dsrag_sdk/__init__.py
dsrag_sdk/chat.py
dsrag_sdk/documents.py
dsrag_sdk/exceptions.py
dsrag_sdk/knowledge_bases.py
dsrag_sdk/main.py
dsrag_sdk-0.0.8.dist-info/METADATA
dsrag_sdk-0.0.8.dist-info/WHEEL
dsrag_sdk-0.0.8.dist-info/top_level.txt
dsrag_sdk-0.0.8.dist-info/RECORD
